<org.apache.fontbox.ttf.GlyfSimpleDescript>
  <instructions>
    <int>64</int>
    <int>59</int>
    <int>147</int>
    <int>3</int>
    <int>1</int>
    <int>147</int>
    <int>2</int>
    <int>1</int>
    <int>153</int>
    <int>16</int>
    <int>1</int>
    <int>150</int>
    <int>0</int>
    <int>1</int>
    <int>141</int>
    <int>16</int>
    <int>157</int>
    <int>16</int>
    <int>2</int>
    <int>141</int>
    <int>0</int>
    <int>157</int>
    <int>0</int>
    <int>2</int>
    <int>122</int>
    <int>29</int>
    <int>138</int>
    <int>29</int>
    <int>154</int>
    <int>29</int>
    <int>3</int>
    <int>105</int>
    <int>29</int>
    <int>1</int>
    <int>157</int>
    <int>30</int>
    <int>1</int>
    <int>30</int>
    <int>16</int>
    <int>13</int>
    <int>16</int>
    <int>72</int>
    <int>146</int>
    <int>19</int>
    <int>1</int>
    <int>134</int>
    <int>19</int>
    <int>1</int>
    <int>114</int>
    <int>19</int>
    <int>1</int>
    <int>86</int>
    <int>19</int>
    <int>102</int>
    <int>19</int>
    <int>2</int>
    <int>146</int>
    <int>18</int>
    <int>1</int>
    <int>3</int>
    <int>18</int>
    <int>184</int>
    <int>255</int>
    <int>240</int>
    <int>64</int>
    <int>36</int>
    <int>13</int>
    <int>16</int>
    <int>72</int>
    <int>16</int>
    <int>0</int>
    <int>24</int>
    <int>8</int>
    <int>24</int>
    <int>8</int>
    <int>24</int>
    <int>17</int>
    <int>30</int>
    <int>31</int>
    <int>16</int>
    <int>153</int>
    <int>31</int>
    <int>1</int>
    <int>134</int>
    <int>31</int>
    <int>1</int>
    <int>89</int>
    <int>31</int>
    <int>1</int>
    <int>70</int>
    <int>31</int>
    <int>1</int>
    <int>25</int>
    <int>31</int>
    <int>1</int>
    <int>6</int>
    <int>31</int>
    <int>1</int>
    <int>8</int>
    <int>31</int>
    <int>18</int>
    <int>17</int>
    <int>184</int>
    <int>255</int>
    <int>240</int>
    <int>64</int>
    <int>36</int>
    <int>17</int>
    <int>6</int>
    <int>33</int>
    <int>1</int>
    <int>6</int>
    <int>33</int>
    <int>38</int>
    <int>33</int>
    <int>54</int>
    <int>33</int>
    <int>70</int>
    <int>33</int>
    <int>102</int>
    <int>33</int>
    <int>118</int>
    <int>33</int>
    <int>134</int>
    <int>33</int>
    <int>166</int>
    <int>33</int>
    <int>182</int>
    <int>33</int>
    <int>198</int>
    <int>33</int>
    <int>230</int>
    <int>33</int>
    <int>246</int>
    <int>33</int>
    <int>12</int>
    <int>199</int>
    <int>230</int>
    <int>33</int>
    <int>246</int>
    <int>33</int>
    <int>2</int>
    <int>33</int>
    <int>184</int>
    <int>255</int>
    <int>192</int>
    <int>64</int>
    <int>255</int>
    <int>217</int>
    <int>233</int>
    <int>72</int>
    <int>196</int>
    <int>33</int>
    <int>1</int>
    <int>166</int>
    <int>33</int>
    <int>182</int>
    <int>33</int>
    <int>2</int>
    <int>132</int>
    <int>33</int>
    <int>1</int>
    <int>6</int>
    <int>33</int>
    <int>38</int>
    <int>33</int>
    <int>54</int>
    <int>33</int>
    <int>70</int>
    <int>33</int>
    <int>102</int>
    <int>33</int>
    <int>118</int>
    <int>33</int>
    <int>6</int>
    <int>6</int>
    <int>33</int>
    <int>38</int>
    <int>33</int>
    <int>54</int>
    <int>33</int>
    <int>70</int>
    <int>33</int>
    <int>102</int>
    <int>33</int>
    <int>118</int>
    <int>33</int>
    <int>134</int>
    <int>33</int>
    <int>166</int>
    <int>33</int>
    <int>182</int>
    <int>33</int>
    <int>198</int>
    <int>33</int>
    <int>230</int>
    <int>33</int>
    <int>246</int>
    <int>33</int>
    <int>12</int>
    <int>6</int>
    <int>33</int>
    <int>22</int>
    <int>33</int>
    <int>38</int>
    <int>33</int>
    <int>70</int>
    <int>33</int>
    <int>86</int>
    <int>33</int>
    <int>102</int>
    <int>33</int>
    <int>134</int>
    <int>33</int>
    <int>166</int>
    <int>33</int>
    <int>198</int>
    <int>33</int>
    <int>230</int>
    <int>33</int>
    <int>246</int>
    <int>33</int>
    <int>11</int>
    <int>151</int>
    <int>244</int>
    <int>33</int>
    <int>1</int>
    <int>224</int>
    <int>33</int>
    <int>1</int>
    <int>194</int>
    <int>33</int>
    <int>210</int>
    <int>33</int>
    <int>2</int>
    <int>180</int>
    <int>33</int>
    <int>1</int>
    <int>160</int>
    <int>33</int>
    <int>1</int>
    <int>130</int>
    <int>33</int>
    <int>146</int>
    <int>33</int>
    <int>2</int>
    <int>116</int>
    <int>33</int>
    <int>1</int>
    <int>96</int>
    <int>33</int>
    <int>1</int>
    <int>66</int>
    <int>33</int>
    <int>82</int>
    <int>33</int>
    <int>2</int>
    <int>52</int>
    <int>33</int>
    <int>1</int>
    <int>32</int>
    <int>33</int>
    <int>1</int>
    <int>2</int>
    <int>33</int>
    <int>18</int>
    <int>33</int>
    <int>2</int>
    <int>228</int>
    <int>33</int>
    <int>244</int>
    <int>33</int>
    <int>2</int>
    <int>194</int>
    <int>33</int>
    <int>210</int>
    <int>33</int>
    <int>2</int>
    <int>164</int>
    <int>33</int>
    <int>180</int>
    <int>33</int>
    <int>2</int>
    <int>130</int>
    <int>33</int>
    <int>146</int>
    <int>33</int>
    <int>2</int>
    <int>100</int>
    <int>33</int>
    <int>116</int>
    <int>33</int>
    <int>2</int>
    <int>66</int>
    <int>33</int>
    <int>82</int>
    <int>33</int>
    <int>2</int>
    <int>36</int>
    <int>33</int>
    <int>52</int>
    <int>33</int>
    <int>2</int>
    <int>2</int>
    <int>33</int>
    <int>18</int>
    <int>33</int>
    <int>2</int>
    <int>228</int>
    <int>33</int>
    <int>244</int>
    <int>33</int>
    <int>2</int>
    <int>194</int>
    <int>33</int>
    <int>210</int>
    <int>33</int>
    <int>2</int>
    <int>164</int>
    <int>33</int>
    <int>180</int>
    <int>33</int>
    <int>2</int>
    <int>130</int>
    <int>33</int>
    <int>146</int>
    <int>33</int>
    <int>2</int>
    <int>100</int>
    <int>33</int>
    <int>116</int>
    <int>33</int>
    <int>2</int>
    <int>86</int>
    <int>33</int>
    <int>1</int>
    <int>66</int>
    <int>33</int>
    <int>1</int>
    <int>36</int>
    <int>33</int>
    <int>52</int>
    <int>33</int>
    <int>2</int>
    <int>22</int>
    <int>33</int>
    <int>1</int>
    <int>2</int>
    <int>33</int>
    <int>1</int>
    <int>103</int>
    <int>228</int>
    <int>33</int>
    <int>244</int>
    <int>33</int>
    <int>2</int>
    <int>214</int>
    <int>33</int>
    <int>1</int>
    <int>194</int>
    <int>33</int>
    <int>1</int>
    <int>164</int>
    <int>33</int>
    <int>180</int>
    <int>33</int>
    <int>2</int>
    <int>150</int>
    <int>33</int>
    <int>1</int>
    <int>130</int>
    <int>33</int>
    <int>1</int>
    <int>100</int>
    <int>33</int>
    <int>116</int>
    <int>33</int>
    <int>2</int>
    <int>86</int>
    <int>33</int>
    <int>1</int>
    <int>66</int>
    <int>33</int>
    <int>1</int>
    <int>36</int>
    <int>33</int>
    <int>52</int>
    <int>33</int>
    <int>2</int>
    <int>22</int>
    <int>33</int>
    <int>1</int>
    <int>2</int>
    <int>33</int>
    <int>1</int>
    <int>228</int>
    <int>33</int>
    <int>244</int>
    <int>33</int>
    <int>2</int>
    <int>214</int>
    <int>33</int>
    <int>1</int>
    <int>64</int>
    <int>166</int>
    <int>194</int>
    <int>33</int>
    <int>1</int>
    <int>1</int>
    <int>160</int>
    <int>33</int>
    <int>176</int>
    <int>33</int>
    <int>2</int>
    <int>132</int>
    <int>33</int>
    <int>148</int>
    <int>33</int>
    <int>2</int>
    <int>96</int>
    <int>33</int>
    <int>112</int>
    <int>33</int>
    <int>2</int>
    <int>68</int>
    <int>33</int>
    <int>84</int>
    <int>33</int>
    <int>2</int>
    <int>32</int>
    <int>33</int>
    <int>48</int>
    <int>33</int>
    <int>2</int>
    <int>4</int>
    <int>33</int>
    <int>20</int>
    <int>33</int>
    <int>2</int>
    <int>224</int>
    <int>33</int>
    <int>240</int>
    <int>33</int>
    <int>2</int>
    <int>196</int>
    <int>33</int>
    <int>212</int>
    <int>33</int>
    <int>2</int>
    <int>160</int>
    <int>33</int>
    <int>176</int>
    <int>33</int>
    <int>2</int>
    <int>132</int>
    <int>33</int>
    <int>148</int>
    <int>33</int>
    <int>2</int>
    <int>96</int>
    <int>33</int>
    <int>112</int>
    <int>33</int>
    <int>2</int>
    <int>68</int>
    <int>33</int>
    <int>84</int>
    <int>33</int>
    <int>2</int>
    <int>32</int>
    <int>33</int>
    <int>48</int>
    <int>33</int>
    <int>2</int>
    <int>4</int>
    <int>33</int>
    <int>20</int>
    <int>33</int>
    <int>2</int>
    <int>55</int>
    <int>224</int>
    <int>33</int>
    <int>1</int>
    <int>196</int>
    <int>33</int>
    <int>212</int>
    <int>33</int>
    <int>2</int>
    <int>160</int>
    <int>33</int>
    <int>1</int>
    <int>132</int>
    <int>33</int>
    <int>148</int>
    <int>33</int>
    <int>2</int>
    <int>96</int>
    <int>33</int>
    <int>1</int>
    <int>68</int>
    <int>33</int>
    <int>84</int>
    <int>33</int>
    <int>2</int>
    <int>32</int>
    <int>33</int>
    <int>1</int>
    <int>4</int>
    <int>33</int>
    <int>20</int>
    <int>33</int>
    <int>2</int>
    <int>224</int>
    <int>33</int>
    <int>1</int>
    <int>196</int>
    <int>33</int>
    <int>212</int>
    <int>33</int>
    <int>2</int>
    <int>160</int>
    <int>33</int>
    <int>1</int>
    <int>132</int>
    <int>33</int>
    <int>148</int>
    <int>33</int>
    <int>2</int>
    <int>96</int>
    <int>33</int>
    <int>1</int>
    <int>2</int>
    <int>0</int>
    <int>33</int>
    <int>32</int>
    <int>33</int>
    <int>48</int>
    <int>33</int>
    <int>80</int>
    <int>33</int>
    <int>4</int>
    <int>80</int>
    <int>33</int>
    <int>128</int>
    <int>33</int>
    <int>144</int>
    <int>33</int>
    <int>192</int>
    <int>33</int>
    <int>4</int>
    <int>47</int>
    <int>33</int>
    <int>1</int>
    <int>0</int>
    <int>33</int>
    <int>16</int>
    <int>33</int>
    <int>2</int>
    <int>7</int>
    <int>16</int>
    <int>0</int>
    <int>24</int>
    <int>0</int>
    <int>32</int>
    <int>30</int>
    <int>17</int>
    <int>15</int>
    <int>12</int>
    <int>80</int>
    <int>5</int>
    <int>27</int>
    <int>0</int>
    <int>63</int>
    <int>237</int>
    <int>63</int>
    <int>51</int>
    <int>17</int>
    <int>51</int>
    <int>51</int>
    <int>17</int>
    <int>51</int>
    <int>1</int>
    <int>94</int>
    <int>93</int>
    <int>93</int>
    <int>93</int>
    <int>113</int>
    <int>95</int>
    <int>113</int>
    <int>113</int>
    <int>113</int>
    <int>113</int>
    <int>113</int>
    <int>114</int>
    <int>114</int>
    <int>114</int>
    <int>114</int>
    <int>114</int>
    <int>114</int>
    <int>114</int>
    <int>114</int>
    <int>94</int>
    <int>93</int>
    <int>93</int>
    <int>93</int>
    <int>93</int>
    <int>93</int>
    <int>93</int>
    <int>93</int>
    <int>93</int>
    <int>113</int>
    <int>113</int>
    <int>113</int>
    <int>113</int>
    <int>113</int>
    <int>113</int>
    <int>95</int>
    <int>113</int>
    <int>113</int>
    <int>113</int>
    <int>114</int>
    <int>114</int>
    <int>114</int>
    <int>114</int>
    <int>114</int>
    <int>114</int>
    <int>114</int>
    <int>114</int>
    <int>114</int>
    <int>114</int>
    <int>114</int>
    <int>114</int>
    <int>94</int>
    <int>93</int>
    <int>93</int>
    <int>93</int>
    <int>93</int>
    <int>93</int>
    <int>93</int>
    <int>93</int>
    <int>93</int>
    <int>93</int>
    <int>93</int>
    <int>113</int>
    <int>113</int>
    <int>113</int>
    <int>113</int>
    <int>113</int>
    <int>113</int>
    <int>113</int>
    <int>113</int>
    <int>114</int>
    <int>114</int>
    <int>114</int>
    <int>114</int>
    <int>114</int>
    <int>114</int>
    <int>114</int>
    <int>114</int>
    <int>114</int>
    <int>114</int>
    <int>114</int>
    <int>114</int>
    <int>94</int>
    <int>93</int>
    <int>113</int>
    <int>114</int>
    <int>114</int>
    <int>114</int>
    <int>114</int>
    <int>43</int>
    <int>114</int>
    <int>94</int>
    <int>93</int>
    <int>113</int>
    <int>47</int>
    <int>56</int>
    <int>51</int>
    <int>47</int>
    <int>94</int>
    <int>93</int>
    <int>93</int>
    <int>93</int>
    <int>93</int>
    <int>93</int>
    <int>93</int>
    <int>56</int>
    <int>51</int>
    <int>18</int>
    <int>57</int>
    <int>57</int>
    <int>61</int>
    <int>47</int>
    <int>24</int>
    <int>47</int>
    <int>17</int>
    <int>51</int>
    <int>51</int>
    <int>49</int>
    <int>48</int>
    <int>43</int>
    <int>95</int>
    <int>93</int>
    <int>93</int>
    <int>93</int>
    <int>93</int>
    <int>93</int>
    <int>43</int>
    <int>93</int>
    <int>93</int>
    <int>93</int>
    <int>0</int>
    <int>93</int>
    <int>93</int>
    <int>1</int>
    <int>93</int>
    <int>93</int>
    <int>93</int>
    <int>93</int>
  </instructions>
  <contourCount>1</contourCount>
  <endPtsOfContours>
    <int>31</int>
  </endPtsOfContours>
  <flags>IQ4ODg4jIiYnNR4eMzI2Pz8BMxMeHh4eFz4+Pj43EzM=</flags>
  <xCoordinates>
    <short>604</short>
    <short>566</short>
    <short>487</short>
    <short>389</short>
    <short>269</short>
    <short>191</short>
    <short>157</short>
    <short>99</short>
    <short>67</short>
    <short>67</short>
    <short>86</short>
    <short>134</short>
    <short>151</short>
    <short>230</short>
    <short>366</short>
    <short>417</short>
    <short>434</short>
    <short>5</short>
    <short>197</short>
    <short>425</short>
    <short>435</short>
    <short>466</short>
    <short>497</short>
    <short>521</short>
    <short>523</short>
    <short>526</short>
    <short>549</short>
    <short>578</short>
    <short>608</short>
    <short>618</short>
    <short>830</short>
    <short>1020</short>
  </xCoordinates>
  <yCoordinates>
    <short>0</short>
    <short>-98</short>
    <short>-255</short>
    <short>-366</short>
    <short>-425</short>
    <short>-425</short>
    <short>-425</short>
    <short>-421</short>
    <short>-414</short>
    <short>-279</short>
    <short>-282</short>
    <short>-285</short>
    <short>-285</short>
    <short>-285</short>
    <short>-167</short>
    <short>-38</short>
    <short>5</short>
    <short>1082</short>
    <short>1082</short>
    <short>484</short>
    <short>457</short>
    <short>367</short>
    <short>277</short>
    <short>205</short>
    <short>196</short>
    <short>207</short>
    <short>272</short>
    <short>352</short>
    <short>434</short>
    <short>464</short>
    <short>1082</short>
    <short>1082</short>
  </yCoordinates>
  <pointCount>32</pointCount>
</org.apache.fontbox.ttf.GlyfSimpleDescript>